pipeline/__init__.py
pipeline/filesystem_pipeline.py
pipeline/pipeline.py
ixp_pipeline-0.1.0.dist-info/LICENSE
ixp_pipeline-0.1.0.dist-info/METADATA
ixp_pipeline-0.1.0.dist-info/WHEEL
ixp_pipeline-0.1.0.dist-info/top_level.txt
ixp_pipeline-0.1.0.dist-info/RECORD
