Metadata-Version: 2.2
Name: ixp_pipeline
Version: 0.1.0
Summary: A Python library for building pipelines with ixp_generics
Author-email: "John S. Azariah" <john.azariah@gmail.com>
License: Creative Commons Legal Code
Keywords: pipeline,workflow,generics
Classifier: Development Status :: 4 - Beta
Classifier: Intended Audience :: Developers
Classifier: License :: OSI Approved :: MIT License
Classifier: Programming Language :: Python
Classifier: Programming Language :: Python :: 3
Classifier: Programming Language :: Python :: 3.12
Requires-Python: >=3.12
License-File: LICENSE
Requires-Dist: ixp_generics>=0.1.0
